{
  "hero": {
    "label": "La tavola del territorio",
    "title": "Il Ristorante",
    "titleItalic": "San Michele",
    "subtitle": "Cucina lombarda d'autore, stagionale e artigianale",
    "img": "/images/hotel-1.jpg"
  },
  "storia": {
    "sectionLabel": "La nostra storia",
    "title": "Una cucina nata",
    "titleItalic": "dal territorio",
    "paragraphs": [
      "Il ristorante San Michele nasce con la stessa visione dell'hotel: portare a tavola il meglio che la Franciacorta e la Lombardia hanno da offrire.La cucina lavora con fornitori locali di fiducia, seguendo il calendario naturale delle stagioni.",
      "Pasta fresca, carne di qualità ,selvaggina e pesce di lago vengono trattati mescolando ricette tradizionali a gusti moderni .",
      "La struttura dispone di una sala da 70 coperti , un ampio salone da 200 posti e una terrazza panoramica che si affaccia su colline e vigneti circostanti . Questi spazi rendono l'hotel il posto ideale per organizzare cerimonie , banchetti , meeting aziendali e feste ."
    ],
    "images": [
      "/images/hotel-1.jpg",
      "/images/hotel-3.jpg",
      "/images/hotel-4.jpg"
    ]
  },
  "filosofia": {
    "sectionLabel": "La filosofia",
    "title": "Tre valori che",
    "titleItalic": "guidano la cucina",
    "cards": [
      {
        "icon": "🌿",
        "title": "Stagionalità rigorosa",
        "body": "Il menu cambia , seguendo il ciclo naturale delle stagioni. Evitiamo prodotti fuori stagione: cerchiamo di scegliere solo ciò che la natura offre nel momento giusto."
      },
      {
        "icon": "🤝",
        "title": "Fornitori di fiducia",
        "body": "Ci affidiamo a fornitori locali , prediligendo prodotti della zona ."
      },
      {
        "icon": "⚗️",
        "title": "Artigianalità e tecnica",
        "body": "La tradizione come punto di partenza, la tecnica contemporanea come strumento. Il risultato: piatti riconoscibili che sorprendono ad ogni assaggio."
      }
    ]
  },
  "signature": {
    "sectionLabel": "I nostri piatti firma",
    "title": "Le",
    "titleItalic": "Specialità",
    "titleSuffix": "del San Michele",
    "dishes": [
      {
        "name": "Risotto al Franciacorta DOCG",
        "desc": "Riso Carnaroli mantecato al Franciacorta Brut, burro di malga e Grana Padano 24 mesi",
        "cat": "Primo Piatto · Firma",
        "img": "/images/hotel-2.jpg"
      },
      {
        "name": "Filetto di Manzo al Tartufo",
        "desc": "Filetto bresciano, salsa al Madeira, scaglie di tartufo nero, gratin di patate",
        "cat": "Secondo Piatto · Firma",
        "img": "/images/hotel-3.jpg"
      },
      {
        "name": "Tiramisù San Michele",
        "desc": "Savoiardi, mascarpone, caffè Arabica, cacao amaro e Amaretto di Saronno",
        "cat": "Dolce · Firma",
        "img": "/images/hotel-4.jpg"
      }
    ]
  },
  "vini": {
    "sectionLabel": "La carta dei vini",
    "title": "Il",
    "titleItalic": "Franciacorta",
    "titleSuffix": "in bottiglia",
    "body1": "Cerchiamo di promuovere il nostro territorio dando la possibilità di degustare i vini prodotti nel nostro comune oltre ai più rinomati produttori del territorio Franciacortino",
    "body2": "Venite a scoprire un mondo di bollicine",
    "img": "/images/cantina-1.jpg"
  },
  "orari": {
    "title": "Orari e Prenotazioni",
    "slots": [
      {
        "label": "Pranzo",
        "value": "Lunedì – Domenica",
        "time": "12:00 – 14:30"
      },
      {
        "label": "Cena",
        "value": "Venerdì – Domenica",
        "time": "19:00 – 22:00"
      },
      {
        "label": "Banchetti",
        "value": "Proponiamo menu dedicati ad ogni esigenza",
        "time": ""
      }
    ]
  }
}
